inapp_file_util/__init__.py
inapp_file_util_rjanoop-1.0.0.dist-info/LICENSE
inapp_file_util_rjanoop-1.0.0.dist-info/METADATA
inapp_file_util_rjanoop-1.0.0.dist-info/WHEEL
inapp_file_util_rjanoop-1.0.0.dist-info/top_level.txt
inapp_file_util_rjanoop-1.0.0.dist-info/RECORD
