Metadata-Version: 2.1
Name: inapp-file-util-rjanoop
Version: 1.0.0
Summary: Utility to read and write raw data file and other utility functions
Home-page: https://github.com/rjanoop/inapp_file_util
Author: RJ Anoop
Author-email: mail.anooprj@gmail.com
License: UNKNOWN
Platform: UNKNOWN
Classifier: Programming Language :: Python :: 3
Classifier: License :: OSI Approved :: MIT License
Classifier: Operating System :: OS Independent
